video2text/__init__.py
video2text/base.py
video2text/downloader.py
video2text/main.py
video2text/whisper_service.py
video2text-0.1.0.dist-info/METADATA
video2text-0.1.0.dist-info/WHEEL
video2text-0.1.0.dist-info/licenses/LICENSE
video2text-0.1.0.dist-info/RECORD
