Metadata-Version: 2.4
Name: video2text
Version: 0.1.0
Summary: A command-line tool to transcribe audio from YouTube and other sources using Whisper.
Author-email: Thaddeus Low <thaddeuslow@outlook.com>
License: MIT
License-File: LICENSE
Requires-Python: >=3.12
Requires-Dist: build>=1.2.2.post1
Requires-Dist: hatchling>=1.27.0
Requires-Dist: marimo>=0.14.9
Requires-Dist: openai-whisper>=20250625
Requires-Dist: yt-dlp>=2025.6.30
